cryoassess/__init__.py
cryoassess/bibtex.py
cryoassess/constants.py
cryoassess/protocols/__init__.py
cryoassess/protocols/protocol_2dassess.py
cryoassess/protocols/protocol_micassess.py
cryoassess/tests/__init__.py
cryoassess/tests/test_protocols_cryoassess.py
scipion_em_cryoassess-3.4.1.dist-info/LICENSE
scipion_em_cryoassess-3.4.1.dist-info/METADATA
scipion_em_cryoassess-3.4.1.dist-info/WHEEL
scipion_em_cryoassess-3.4.1.dist-info/entry_points.txt
scipion_em_cryoassess-3.4.1.dist-info/top_level.txt
scipion_em_cryoassess-3.4.1.dist-info/RECORD
