Metadata-Version: 2.1
Name: scipion-em-cryoassess
Version: 3.4.1
Summary: Plugin to use cryoassess programs within the Scipion framework
Author-email: Scipion Team <scipion@cnb.csic.es>
License: GNU General Public License v3 (GPLv3)
Project-URL: Homepage, https://github.com/scipion-em/scipion-em-cryoassess
Project-URL: Issues, https://github.com/scipion-em/scipion-em-cryoassess/issues
Keywords: scipion,cryoem,imageprocessing,scipion-3.0
Classifier: Development Status :: 5 - Production/Stable
Classifier: License :: OSI Approved :: GNU General Public License v3 (GPLv3)
Classifier: Programming Language :: Python :: 3
Requires-Python: >=3.8
License-File: LICENSE
Requires-Dist: scipion-em
Requires-Dist: scipion-pyworkflow
Requires-Dist: emtable
